mltoarduino/__init__.py
mltoarduino/src/__init__.py
mltoarduino/src/mltoarduino.py
mltoarduino/test/__init__.py
mltoarduino/test/test_mltoarduino.py
mltoarduino-0.0.7.dist-info/LICENSE
mltoarduino-0.0.7.dist-info/METADATA
mltoarduino-0.0.7.dist-info/WHEEL
mltoarduino-0.0.7.dist-info/top_level.txt
mltoarduino-0.0.7.dist-info/RECORD
