Metadata-Version: 2.1
Name: mltoarduino
Version: 0.0.7
Summary: See readMe.ma
Home-page: https://github.com/bouz1/PypiContributions/tree/main/mltoarduino
Author: bouz1.github.io
Author-email: bozzabb1@gmail.com
License: MIT
Platform: UNKNOWN
Classifier: License :: OSI Approved :: MIT License
Classifier: Programming Language :: Python :: 3.10
Classifier: Operating System :: OS Independent
Requires-Python: >=3.1
License-File: LICENSE
Provides-Extra: dev
Requires-Dist: pyperclip ; extra == 'dev'
Requires-Dist: pandas ; extra == 'dev'
Requires-Dist: numpy ; extra == 'dev'
